approxism
