Metadata-Version: 2.1
Name: approxism
Version: 0.1.1
Summary: Approximate String Matching using libsdcxx
Home-page: https://github.com/vencik/approxism
Author: Václav Krpec
Author-email: vencik@razdva.cz
License: BSD-3-Clause license
Platform: UNKNOWN
Classifier: Development Status :: 4 - Beta
Classifier: Intended Audience :: Developers
Classifier: Topic :: Text Processing
Classifier: License :: OSI Approved :: BSD License
Classifier: Programming Language :: Python :: 3
